Metadata-Version: 2.1
Name: pyside6-expand
Version: 1.0.1
Summary: A expand about pyside6
Home-page: https://github.com/yjfw-developer/pyside6-expand.git
Author: yjfw
Author-email: yjfw_developer@163.com
License: Apache
Requires-Python: >=3.6
Requires-Dist: PySide6
